{"singlePage": [], "startSite": "", "filingNum": "", "onePageListNum": 15, "commentLabelColor": "#006b75", "yearColorList": ["#bc4c00", "#0969da", "#1f883d", "#A333D0"], "i18n": "CN", "themeMode": "manual", "dayTheme": "light", "nightTheme": "dark", "urlMode": "pinyin", "script": "", "style": "", "head": "", "indexScript": "", "indexStyle": "", "bottomText": "", "showPostSource": 1, "iconList": {}, "UTC": 8, "rssSplit": "sentence", "exlink": {}, "needComment": 1, "allHead": "", "title": "\u60f3\u8c61\u7684\u4e16\u754c", "subTitle": "\u5404\u7c7b\u8f6f\u4ef6\u5206\u4eab", "avatarUrl": "https://avatars.githubusercontent.com/u/37973119?s=400&u=15cd99dc9f1299ffff5815ce7641002df3cc82b9&v=4", "GMEEK_VERSION": "last", "postListJson": {"P1": {"htmlDir": "docs/post/ruan-jian-fen-xiang-_-ben-di-wu-xu-lian-wang-\uff0c-qu-chu-bei-jing-AI-yi-jian-kou-tu.html", "labels": ["good first issue", "invalid"], "postTitle": "\u8f6f\u4ef6\u5206\u4eab_\u672c\u5730\u65e0\u9700\u8054\u7f51\uff0c\u53bb\u9664\u80cc\u666fAI\u4e00\u952e\u62a0\u56fe", "postUrl": "post/ruan-jian-fen-xiang-_-ben-di-wu-xu-lian-wang-%EF%BC%8C-qu-chu-bei-jing-AI-yi-jian-kou-tu.html", "postSourceUrl": "https://github.com/qsjyqs/qsjyqs.github.io/issues/1", "commentNum": 0, "wordCount": 186, "description": "### \u672c\u5730\u65e0\u9700\u8054\u7f51\uff0c\u53bb\u9664\u80cc\u666fAI\u4e00\u952e\u62a0\u56fe\r\n**\u6709Windows\u548cMac\u7248\u672c**\r\n[https://www.123pan.com/s/LZamjv-WZnjd.html](url)\r\n![AI\u62a0\u56fe\u5c55\u793a](https://github.com/user-attachments/assets/c9a90f4c-a2ae-41b8-9c56-11ee5c9bbf4e)\r\n\u3002", "top": 0, "createdAt": 1721805449, "style": "", "script": "", "head": "", "ogImage": "https://avatars.githubusercontent.com/u/37973119?s=400&u=15cd99dc9f1299ffff5815ce7641002df3cc82b9&v=4", "createdDate": "2024-07-24", "dateLabelColor": "#bc4c00"}}, "singeListJson": {}, "labelColorDict": {"bug": "#d73a4a", "documentation": "#0075ca", "duplicate": "#cfd3d7", "enhancement": "#a2eeef", "good first issue": "#7057ff", "help wanted": "#008672", "invalid": "#e4e669", "question": "#d876e3", "wontfix": "#ffffff"}, "displayTitle": "\u60f3\u8c61\u7684\u4e16\u754c", "faviconUrl": "https://avatars.githubusercontent.com/u/37973119?s=400&u=15cd99dc9f1299ffff5815ce7641002df3cc82b9&v=4", "ogImage": "https://avatars.githubusercontent.com/u/37973119?s=400&u=15cd99dc9f1299ffff5815ce7641002df3cc82b9&v=4", "primerCSS": "<link href='https://mirrors.sustech.edu.cn/cdnjs/ajax/libs/Primer/21.0.7/primer.css' rel='stylesheet' />", "homeUrl": "https://qsjyqs.github.io", "prevUrl": "disabled", "nextUrl": "disabled"}